pin_py/__init__.py
pin_py/pinterest/__init__.py
pin_py/pinterest/pinpy.py
pin_py/utils/__init__.py
pin_py/utils/config.py
pin_py/utils/http.py
pin_py/utils/settings.py
pin_py-0.0.7.dist-info/METADATA
pin_py-0.0.7.dist-info/RECORD
pin_py-0.0.7.dist-info/WHEEL
pin_py-0.0.7.dist-info/top_level.txt
