Metadata-Version: 2.1
Name: pin-py
Version: 0.0.7
Summary: Python wrapper for pinterest API
Home-page: https://github.com/d4interactive/pinterest-api
Author: Hassan Alvi
Author-email: hassan.awan@d4interactive.io
License: UNKNOWN
Platform: UNKNOWN
Classifier: Programming Language :: Python :: 3
Classifier: License :: OSI Approved :: MIT License
Classifier: Operating System :: OS Independent
